aws_saving/__init__.py
aws_saving/cloudformation.py
aws_saving/ec2.py
aws_saving/ecr.py
aws_saving/rds.py
aws_saving/s3.py
aws_saving/sagemaker_studio.py
aws_saving/saving.py
aws_saving/service.py
tests/__init__.py
tests/helper.py
tests/integration_test_all_services.py
tests/integration_test_only_cloudformation.py
tests/test_cloudformation.py
tests/test_ec2.py
tests/test_ecr.py
tests/test_rds.py
tests/test_s3.py
tests/test_sagemaker_studio.py
tests/test_saving.py
tests/test_service.py
aws_saving-1.1.3.dist-info/LICENSE
aws_saving-1.1.3.dist-info/METADATA
aws_saving-1.1.3.dist-info/WHEEL
aws_saving-1.1.3.dist-info/top_level.txt
aws_saving-1.1.3.dist-info/RECORD
