Metadata-Version: 2.1
Name: aws-saving
Version: 1.1.3
Summary: AWS saving Python package
Home-page: https://aws-saving.readthedocs.io/
Author: Alessandra Bilardi
Author-email: alessandra.bilardi@gmail.com
License: UNKNOWN
Project-URL: Source, https://github.com/bilardi/aws-saving
Project-URL: Bug Reports, https://github.com/bilardi/aws-saving/issues
Project-URL: Funding, https://donate.pypi.org
Platform: UNKNOWN
Classifier: Programming Language :: Python :: 3
Classifier: License :: OSI Approved :: MIT License
Classifier: Operating System :: OS Independent
Requires-Python: >=3.6
